LightGBMwithBayesOpt/LightGBMwithBayesOpt.py
LightGBMwithBayesOpt/__init__.py
LightGBMwithBayesOpt-1.0.2.dist-info/LICENSE
LightGBMwithBayesOpt-1.0.2.dist-info/METADATA
LightGBMwithBayesOpt-1.0.2.dist-info/WHEEL
LightGBMwithBayesOpt-1.0.2.dist-info/top_level.txt
LightGBMwithBayesOpt-1.0.2.dist-info/RECORD
